libtimecontrol/__init__.py
libtimecontrol/libtimecontrol.py
libtimecontrol/path.py
libtimecontrol/bin/test_prog
libtimecontrol/bin/test_prog32
libtimecontrol/bin/test_prog_dlsym
libtimecontrol/bin/test_prog_dlsym32
libtimecontrol/integration_tests/integration_test.py
libtimecontrol/lib/libtime_control.so
libtimecontrol/lib/libtime_control32.so
libtimecontrol/lib/libtime_control_dlsym.so
libtimecontrol/lib/libtime_control_dlsym32.so
libtimecontrol/lib/libtime_controller.so
libtimecontrol/microbenchmark/bench.c
libtimecontrol/microbenchmark/benchmarks.py
libtimecontrol/microbenchmark/run_bench.sh
libtimecontrol/microbenchmark/run_benchmark.py
libtimecontrol/microbenchmark/cffi_api/build.py
libtimecontrol/microbenchmark/out/benchmark.txt
libtimecontrol-0.1.5.dist-info/LICENSE
libtimecontrol-0.1.5.dist-info/METADATA
libtimecontrol-0.1.5.dist-info/WHEEL
libtimecontrol-0.1.5.dist-info/RECORD
