Metadata-Version: 2.3
Name: libtimecontrol
Version: 0.1.5
Summary: An experimental library for controlling the speed of time in Linux child processes
License: MIT
Author: William Henning
Author-email: wchenningwchenning@gmail.com
Requires-Python: >=3.9
Classifier: License :: OSI Approved :: MIT License
Classifier: Programming Language :: Python :: 3
Classifier: Programming Language :: Python :: 3.9
Classifier: Programming Language :: Python :: 3.10
Classifier: Programming Language :: Python :: 3.11
Classifier: Programming Language :: Python :: 3.12
Classifier: Programming Language :: Python :: 3.13
Requires-Dist: cffi (>=1.17.1,<2.0.0)
